sexpr/__init__.py
sexpr/grammar.py
sexpr/loaders.py
sexpr/matcher.py
sexpr/print.py
sexpr/sexpr.py
sexpr/utils.py
sexpr/yaml.py
sexpr/types/__init__.py
sexpr/types/alternative.py
sexpr/types/multiple.py
sexpr/types/non_terminal.py
sexpr/types/reference.py
sexpr/types/rule.py
sexpr/types/sequence.py
sexpr/types/terminal.py
sexpr-0.2.0.dist-info/LICENSE
sexpr-0.2.0.dist-info/METADATA
sexpr-0.2.0.dist-info/WHEEL
sexpr-0.2.0.dist-info/top_level.txt
sexpr-0.2.0.dist-info/RECORD
