Metadata-Version: 2.1
Name: sexpr
Version: 0.2.0
Summary: S-expression toolkit for Python
Home-page: http://github.com/IwoHerka/sexpr
Author: Iwo Herka
Author-email: hi@iwoherka.eu
Maintainer: Iwo Herka
Maintainer-email: hi@iwoherka.eu
License: MIT
Platform: UNKNOWN
Classifier: Development Status :: 2 - Pre-Alpha
Classifier: Intended Audience :: Developers
Classifier: License :: OSI Approved :: MIT License
Classifier: Programming Language :: Python
Classifier: Topic :: Software Development :: Libraries :: Python Modules
Requires: python (>= 3.4)
Provides: sexpr
Requires-Dist: pyyaml (==3.12)
Requires-Dist: yamlloader (==0.5.2)
